{
  "ticker": "AVB",
  "market": "US",
  "last_updated": "2026-07-15T16:17:02Z",
  "data_stale": false,
  "timeframes": {
    "daily": {
      "signal": "HOLD",
      "score": 60.0,
      "reason": "Neutral zone (60.0) | Bullish divergence detected",
      "components": {
        "rsi_stoch": 50.0,
        "divergence": 90.0,
        "candle_pattern": 50.0,
        "bb_touch": 50.0,
        "volume_climax": 50.0,
        "sr_fib": 50.0
      },
      "indicators": {
        "rsi": 57.2354,
        "stoch_k": 67.0348,
        "stoch_d": 69.983,
        "macd": 2.6806,
        "macd_signal": 2.5095,
        "macd_hist": 0.1711,
        "bb_upper": 199.8538,
        "bb_mid": 187.6223,
        "bb_lower": 175.3908,
        "atr": 3.5536,
        "ma50": 185.2188,
        "ma200": 176.5369,
        "price": 191.93,
        "vol_ratio": 0.15,
        "above_ma50": true,
        "above_ma200": true
      },
      "patterns": {
        "candle": {
          "name": null,
          "direction": null
        },
        "bullish_divergence": true,
        "bearish_divergence": false,
        "bb_touch": "none",
        "volume_climax": false,
        "near_support": false,
        "near_resistance": false,
        "in_fib_zone": false
      },
      "trade_levels": {
        "entry": null,
        "stop_loss": null,
        "tp1": null,
        "tp2": null,
        "tp3": null,
        "risk": null,
        "rr_ratio": null,
        "trailing_stop": null,
        "trailing_k": 2.5
      },
      "support_levels": [
        179.03,
        157.3
      ],
      "resistance_levels": [
        186.34,
        175.64
      ],
      "fib_levels": {
        "0.0": 198.63,
        "23.6": 188.83,
        "38.2": 182.77,
        "50.0": 177.87,
        "61.8": 172.98,
        "78.6": 166.0,
        "100.0": 157.12
      }
    },
    "weekly": {
      "signal": "HOLD",
      "score": 47.6,
      "reason": "Neutral zone (47.6)",
      "components": {
        "rsi_stoch": 41.7,
        "divergence": 50.0,
        "candle_pattern": 50.0,
        "bb_touch": 50.0,
        "volume_climax": 50.0,
        "sr_fib": 45.0
      },
      "indicators": {
        "rsi": 59.8641,
        "stoch_k": 86.6347,
        "stoch_d": 88.1752,
        "macd": 4.0785,
        "macd_signal": 2.0321,
        "macd_hist": 2.0463,
        "bb_upper": 199.8519,
        "bb_mid": 177.7209,
        "bb_lower": 155.5898,
        "atr": 7.9007,
        "ma50": 178.0547,
        "ma200": NaN,
        "price": 191.93,
        "vol_ratio": 0.39,
        "above_ma50": true,
        "above_ma200": null
      },
      "patterns": {
        "candle": {
          "name": null,
          "direction": null
        },
        "bullish_divergence": false,
        "bearish_divergence": false,
        "bb_touch": "none",
        "volume_climax": false,
        "near_support": false,
        "near_resistance": true,
        "in_fib_zone": true
      },
      "trade_levels": {
        "entry": null,
        "stop_loss": null,
        "tp1": null,
        "tp2": null,
        "tp3": null,
        "risk": null,
        "rr_ratio": null,
        "trailing_stop": null,
        "trailing_k": 2.5
      },
      "support_levels": [
        167.75,
        200.38
      ],
      "resistance_levels": [
        185.26,
        220.77,
        201.77
      ],
      "fib_levels": {
        "0.0": 224.56,
        "23.6": 208.64,
        "38.2": 198.8,
        "50.0": 190.84,
        "61.8": 182.88,
        "78.6": 171.55,
        "100.0": 157.12
      }
    }
  },
  "yearly_trend": {
    "bias": "volatile",
    "ma200_position": "above",
    "structure": "expanding (HH+LL)",
    "description": "Long-term trend bias \u2014 not a reversal call"
  }
}