{
  "ticker": "BLDR",
  "market": "US",
  "last_updated": "2026-07-14T12:29:14Z",
  "data_stale": false,
  "timeframes": {
    "daily": {
      "signal": "HOLD",
      "score": 55.8,
      "reason": "Neutral zone (55.8)",
      "components": {
        "rsi_stoch": 63.8,
        "divergence": 50.0,
        "candle_pattern": 50.0,
        "bb_touch": 50.0,
        "volume_climax": 50.0,
        "sr_fib": 70.0
      },
      "indicators": {
        "rsi": 39.8684,
        "stoch_k": 8.9494,
        "stoch_d": 9.9564,
        "macd": -0.5477,
        "macd_signal": 0.8627,
        "macd_hist": -1.4104,
        "bb_upper": 92.0348,
        "bb_mid": 80.826,
        "bb_lower": 69.6172,
        "atr": 4.1479,
        "ma50": 77.1768,
        "ma200": 99.406,
        "price": 73.51,
        "vol_ratio": 0.67,
        "above_ma50": false,
        "above_ma200": false
      },
      "patterns": {
        "candle": {
          "name": null,
          "direction": null
        },
        "bullish_divergence": false,
        "bearish_divergence": false,
        "bb_touch": "none",
        "volume_climax": false,
        "near_support": true,
        "near_resistance": false,
        "in_fib_zone": false
      },
      "trade_levels": {
        "entry": null,
        "stop_loss": null,
        "tp1": null,
        "tp2": null,
        "tp3": null,
        "risk": null,
        "rr_ratio": null,
        "trailing_stop": null,
        "trailing_k": 2.5
      },
      "support_levels": [
        75.05
      ],
      "resistance_levels": [
        87.87
      ],
      "fib_levels": {
        "0.0": 117.34,
        "23.6": 105.01,
        "38.2": 97.38,
        "50.0": 91.22,
        "61.8": 85.06,
        "78.6": 76.28,
        "100.0": 65.1
      }
    },
    "weekly": {
      "signal": "HOLD",
      "score": 60.0,
      "reason": "Neutral zone (60.0) | Bullish divergence detected",
      "components": {
        "rsi_stoch": 50.0,
        "divergence": 90.0,
        "candle_pattern": 50.0,
        "bb_touch": 50.0,
        "volume_climax": 50.0,
        "sr_fib": 50.0
      },
      "indicators": {
        "rsi": 39.0337,
        "stoch_k": 43.0644,
        "stoch_d": 56.5153,
        "macd": -7.4993,
        "macd_signal": -8.6029,
        "macd_hist": 1.1036,
        "bb_upper": 93.7779,
        "bb_mid": 80.7395,
        "bb_lower": 67.7011,
        "atr": 9.3882,
        "ma50": 104.2984,
        "ma200": NaN,
        "price": 73.51,
        "vol_ratio": 0.13,
        "above_ma50": false,
        "above_ma200": null
      },
      "patterns": {
        "candle": {
          "name": null,
          "direction": null
        },
        "bullish_divergence": true,
        "bearish_divergence": false,
        "bb_touch": "none",
        "volume_climax": false,
        "near_support": false,
        "near_resistance": false,
        "in_fib_zone": false
      },
      "trade_levels": {
        "entry": null,
        "stop_loss": null,
        "tp1": null,
        "tp2": null,
        "tp3": null,
        "risk": null,
        "rr_ratio": null,
        "trailing_stop": null,
        "trailing_k": 2.5
      },
      "support_levels": [
        107.68
      ],
      "resistance_levels": [
        129.54,
        198.75
      ],
      "fib_levels": {
        "0.0": 203.14,
        "23.6": 170.56,
        "38.2": 150.41,
        "50.0": 134.12,
        "61.8": 117.83,
        "78.6": 94.64,
        "100.0": 65.1
      }
    }
  },
  "yearly_trend": {
    "bias": "consolidating",
    "ma200_position": "below",
    "structure": "contracting (LH+HL)",
    "description": "Long-term trend bias \u2014 not a reversal call"
  }
}