{
  "ticker": "BRIS.JK",
  "market": "IHSG",
  "last_updated": "2026-07-21T16:19:11Z",
  "data_stale": false,
  "timeframes": {
    "daily": {
      "signal": "WATCH",
      "score": 38.2,
      "reason": "Depressed score (38.2) but not at confirmed range high",
      "components": {
        "rsi_stoch": 43.6,
        "divergence": 50.0,
        "candle_pattern": 50.0,
        "bb_touch": 15.0,
        "volume_climax": 50.0,
        "sr_fib": 15.0
      },
      "indicators": {
        "rsi": 59.4082,
        "stoch_k": 85.119,
        "stoch_d": 73.1349,
        "macd": 10.9105,
        "macd_signal": -10.7546,
        "macd_hist": 21.6651,
        "bb_upper": 1897.2665,
        "bb_mid": 1760.0,
        "bb_lower": 1622.7335,
        "atr": 70.4553,
        "ma50": 1802.2082,
        "ma200": 2144.5754,
        "price": 1900.0,
        "vol_ratio": 1.05,
        "above_ma50": true,
        "above_ma200": false
      },
      "patterns": {
        "candle": {
          "name": null,
          "direction": null
        },
        "bullish_divergence": false,
        "bearish_divergence": false,
        "bb_touch": "upper",
        "volume_climax": false,
        "near_support": false,
        "near_resistance": true,
        "in_fib_zone": true
      },
      "trade_levels": {
        "entry": null,
        "stop_loss": null,
        "tp1": null,
        "tp2": null,
        "tp3": null,
        "risk": null,
        "rr_ratio": null,
        "trailing_stop": null,
        "trailing_k": 2.5
      },
      "support_levels": [
        1709.41,
        2046.64
      ],
      "resistance_levels": [
        1961.04,
        2131.09
      ],
      "fib_levels": {
        "0.0": 2356.97,
        "23.6": 2170.07,
        "38.2": 2054.44,
        "50.0": 1960.99,
        "61.8": 1867.53,
        "78.6": 1734.48,
        "100.0": 1565.0
      }
    },
    "weekly": {
      "signal": "HOLD",
      "score": 53.0,
      "reason": "Neutral zone (53.0)",
      "components": {
        "rsi_stoch": 50.0,
        "divergence": 50.0,
        "candle_pattern": 50.0,
        "bb_touch": 50.0,
        "volume_climax": 50.0,
        "sr_fib": 70.0
      },
      "indicators": {
        "rsi": 46.47,
        "stoch_k": 53.2129,
        "stoch_d": 41.7305,
        "macd": -108.5408,
        "macd_signal": -127.5471,
        "macd_hist": 19.0062,
        "bb_upper": 2166.0645,
        "bb_mid": 1897.0217,
        "bb_lower": 1627.9789,
        "atr": 161.5651,
        "ma50": 2197.1498,
        "ma200": NaN,
        "price": 1900.0,
        "vol_ratio": 0.55,
        "above_ma50": false,
        "above_ma200": null
      },
      "patterns": {
        "candle": {
          "name": null,
          "direction": null
        },
        "bullish_divergence": false,
        "bearish_divergence": false,
        "bb_touch": "none",
        "volume_climax": false,
        "near_support": true,
        "near_resistance": false,
        "in_fib_zone": false
      },
      "trade_levels": {
        "entry": null,
        "stop_loss": null,
        "tp1": null,
        "tp2": null,
        "tp3": null,
        "risk": null,
        "rr_ratio": null,
        "trailing_stop": null,
        "trailing_k": 2.5
      },
      "support_levels": [
        2013.05,
        2447.77
      ],
      "resistance_levels": [
        2903.5
      ],
      "fib_levels": {
        "0.0": 3264.62,
        "23.6": 2863.51,
        "38.2": 2615.36,
        "50.0": 2414.81,
        "61.8": 2214.25,
        "78.6": 1928.72,
        "100.0": 1565.0
      }
    }
  },
  "yearly_trend": {
    "bias": "neutral",
    "ma200_position": "below",
    "structure": "mixed",
    "description": "Long-term trend bias \u2014 not a reversal call"
  }
}