{
  "ticker": "CNC",
  "market": "US",
  "last_updated": "2026-07-22T16:18:07Z",
  "data_stale": false,
  "timeframes": {
    "daily": {
      "signal": "HOLD",
      "score": 40.0,
      "reason": "Neutral zone (40.0) | Bearish divergence detected",
      "components": {
        "rsi_stoch": 50.0,
        "divergence": 10.0,
        "candle_pattern": 50.0,
        "bb_touch": 50.0,
        "volume_climax": 50.0,
        "sr_fib": 50.0
      },
      "indicators": {
        "rsi": 54.9914,
        "stoch_k": 57.4134,
        "stoch_d": 49.5129,
        "macd": 1.2767,
        "macd_signal": 1.6224,
        "macd_hist": -0.3456,
        "bb_upper": 69.5596,
        "bb_mid": 66.339,
        "bb_lower": 63.1184,
        "atr": 2.3473,
        "ma50": 63.0098,
        "ma200": 45.7175,
        "price": 66.78,
        "vol_ratio": 0.24,
        "above_ma50": true,
        "above_ma200": true
      },
      "patterns": {
        "candle": {
          "name": null,
          "direction": null
        },
        "bullish_divergence": false,
        "bearish_divergence": true,
        "bb_touch": "none",
        "volume_climax": false,
        "near_support": false,
        "near_resistance": false,
        "in_fib_zone": false
      },
      "trade_levels": {
        "entry": null,
        "stop_loss": null,
        "tp1": null,
        "tp2": null,
        "tp3": null,
        "risk": null,
        "rr_ratio": null,
        "trailing_stop": null,
        "trailing_k": 2.5
      },
      "support_levels": [
        58.02,
        32.74
      ],
      "resistance_levels": [
        60.25,
        69.33
      ],
      "fib_levels": {
        "0.0": 69.36,
        "23.6": 60.46,
        "38.2": 54.95,
        "50.0": 50.49,
        "61.8": 46.04,
        "78.6": 39.7,
        "100.0": 31.63
      }
    },
    "weekly": {
      "signal": "HOLD",
      "score": 43.9,
      "reason": "Neutral zone (43.9)",
      "components": {
        "rsi_stoch": 34.5,
        "divergence": 50.0,
        "candle_pattern": 50.0,
        "bb_touch": 50.0,
        "volume_climax": 50.0,
        "sr_fib": 30.0
      },
      "indicators": {
        "rsi": 69.9752,
        "stoch_k": 92.408,
        "stoch_d": 94.1206,
        "macd": 7.0263,
        "macd_signal": 5.8608,
        "macd_hist": 1.1655,
        "bb_upper": 79.9437,
        "bb_mid": 53.113,
        "bb_lower": 26.2823,
        "atr": 4.4751,
        "ma50": 44.002,
        "ma200": NaN,
        "price": 66.78,
        "vol_ratio": 0.27,
        "above_ma50": true,
        "above_ma200": null
      },
      "patterns": {
        "candle": {
          "name": null,
          "direction": null
        },
        "bullish_divergence": false,
        "bearish_divergence": false,
        "bb_touch": "none",
        "volume_climax": false,
        "near_support": false,
        "near_resistance": true,
        "in_fib_zone": false
      },
      "trade_levels": {
        "entry": null,
        "stop_loss": null,
        "tp1": null,
        "tp2": null,
        "tp3": null,
        "risk": null,
        "rr_ratio": null,
        "trailing_stop": null,
        "trailing_k": 2.5
      },
      "support_levels": [
        33.52,
        55.42
      ],
      "resistance_levels": [
        65.66,
        46.44
      ],
      "fib_levels": {
        "0.0": 80.59,
        "23.6": 67.49,
        "38.2": 59.39,
        "50.0": 52.83,
        "61.8": 46.28,
        "78.6": 36.96,
        "100.0": 25.08
      }
    }
  },
  "yearly_trend": {
    "bias": "bullish",
    "ma200_position": "above",
    "structure": "uptrend (HH+HL)",
    "description": "Long-term trend bias \u2014 not a reversal call"
  }
}