{
  "ticker": "FDS",
  "market": "US",
  "last_updated": "2026-07-20T06:10:22Z",
  "data_stale": false,
  "timeframes": {
    "daily": {
      "signal": "WATCH",
      "score": 36.0,
      "reason": "Depressed score (36.0) but not at confirmed range high | Bearish divergence detected",
      "components": {
        "rsi_stoch": 45.2,
        "divergence": 10.0,
        "candle_pattern": 50.0,
        "bb_touch": 50.0,
        "volume_climax": 50.0,
        "sr_fib": 30.0
      },
      "indicators": {
        "rsi": 57.7049,
        "stoch_k": 83.8575,
        "stoch_d": 85.1271,
        "macd": 6.5214,
        "macd_signal": 4.7699,
        "macd_hist": 1.7515,
        "bb_upper": 274.1621,
        "bb_mid": 240.461,
        "bb_lower": 206.7599,
        "atr": 12.7186,
        "ma50": 235.8123,
        "ma200": 246.8517,
        "price": 258.09,
        "vol_ratio": 1.31,
        "above_ma50": true,
        "above_ma200": true
      },
      "patterns": {
        "candle": {
          "name": null,
          "direction": null
        },
        "bullish_divergence": false,
        "bearish_divergence": true,
        "bb_touch": "none",
        "volume_climax": false,
        "near_support": false,
        "near_resistance": true,
        "in_fib_zone": false
      },
      "trade_levels": {
        "entry": null,
        "stop_loss": null,
        "tp1": null,
        "tp2": null,
        "tp3": null,
        "risk": null,
        "rr_ratio": null,
        "trailing_stop": null,
        "trailing_k": 2.5
      },
      "support_levels": [
        204.06
      ],
      "resistance_levels": [
        235.37,
        212.86,
        267.09
      ],
      "fib_levels": {
        "0.0": 272.4,
        "23.6": 252.39,
        "38.2": 240.01,
        "50.0": 230.01,
        "61.8": 220.01,
        "78.6": 205.76,
        "100.0": 187.62
      }
    },
    "weekly": {
      "signal": "HOLD",
      "score": 50.0,
      "reason": "Neutral zone (50.0)",
      "components": {
        "rsi_stoch": 50.0,
        "divergence": 50.0,
        "candle_pattern": 50.0,
        "bb_touch": 50.0,
        "volume_climax": 50.0,
        "sr_fib": 50.0
      },
      "indicators": {
        "rsi": 54.1189,
        "stoch_k": 72.6164,
        "stoch_d": 62.6419,
        "macd": -4.1835,
        "macd_signal": -11.1139,
        "macd_hist": 6.9305,
        "bb_upper": 262.7564,
        "bb_mid": 228.4407,
        "bb_lower": 194.1251,
        "atr": 24.505,
        "ma50": 263.4303,
        "ma200": NaN,
        "price": 258.09,
        "vol_ratio": 1.0,
        "above_ma50": false,
        "above_ma200": null
      },
      "patterns": {
        "candle": {
          "name": null,
          "direction": null
        },
        "bullish_divergence": false,
        "bearish_divergence": false,
        "bb_touch": "none",
        "volume_climax": false,
        "near_support": true,
        "near_resistance": true,
        "in_fib_zone": false
      },
      "trade_levels": {
        "entry": null,
        "stop_loss": null,
        "tp1": null,
        "tp2": null,
        "tp3": null,
        "risk": null,
        "rr_ratio": null,
        "trailing_stop": null,
        "trailing_k": 2.5
      },
      "support_levels": [
        194.61,
        256.3
      ],
      "resistance_levels": [
        467.06,
        291.44,
        237.52
      ],
      "fib_levels": {
        "0.0": 488.16,
        "23.6": 416.18,
        "38.2": 371.65,
        "50.0": 335.66,
        "61.8": 299.67,
        "78.6": 248.43,
        "100.0": 183.16
      }
    }
  },
  "yearly_trend": {
    "bias": "bullish",
    "ma200_position": "below",
    "structure": "uptrend (HH+HL)",
    "description": "Long-term trend bias \u2014 not a reversal call"
  }
}