{
  "ticker": "GOOGL",
  "market": "US",
  "last_updated": "2026-07-15T16:16:54Z",
  "data_stale": false,
  "timeframes": {
    "daily": {
      "signal": "HOLD",
      "score": 50.0,
      "reason": "Neutral zone (50.0)",
      "components": {
        "rsi_stoch": 50.0,
        "divergence": 50.0,
        "candle_pattern": 50.0,
        "bb_touch": 50.0,
        "volume_climax": 50.0,
        "sr_fib": 50.0
      },
      "indicators": {
        "rsi": 57.7968,
        "stoch_k": 72.9205,
        "stoch_d": 64.8045,
        "macd": -0.6239,
        "macd_signal": -2.1963,
        "macd_hist": 1.5724,
        "bb_upper": 377.3152,
        "bb_mid": 357.7735,
        "bb_lower": 338.2318,
        "atr": 10.663,
        "ma50": 371.9181,
        "ma200": 320.2862,
        "price": 372.56,
        "vol_ratio": 0.37,
        "above_ma50": true,
        "above_ma200": true
      },
      "patterns": {
        "candle": {
          "name": null,
          "direction": null
        },
        "bullish_divergence": false,
        "bearish_divergence": false,
        "bb_touch": "none",
        "volume_climax": false,
        "near_support": true,
        "near_resistance": true,
        "in_fib_zone": false
      },
      "trade_levels": {
        "entry": null,
        "stop_loss": null,
        "tp1": null,
        "tp2": null,
        "tp3": null,
        "risk": null,
        "rr_ratio": null,
        "trailing_stop": null,
        "trailing_k": 2.5
      },
      "support_levels": [
        351.77,
        297.08,
        330.68,
        382.04
      ],
      "resistance_levels": [
        315.14,
        374.58
      ],
      "fib_levels": {
        "0.0": 408.37,
        "23.6": 376.17,
        "38.2": 356.25,
        "50.0": 340.16,
        "61.8": 324.06,
        "78.6": 301.14,
        "100.0": 271.95
      }
    },
    "weekly": {
      "signal": "HOLD",
      "score": 46.0,
      "reason": "Neutral zone (46.0) | Bearish divergence detected | Candle: bullish_engulfing (bullish)",
      "components": {
        "rsi_stoch": 50.0,
        "divergence": 10.0,
        "candle_pattern": 90.0,
        "bb_touch": 50.0,
        "volume_climax": 50.0,
        "sr_fib": 50.0
      },
      "indicators": {
        "rsi": 59.5346,
        "stoch_k": 60.287,
        "stoch_d": 59.0049,
        "macd": 17.8412,
        "macd_signal": 20.9444,
        "macd_hist": -3.1032,
        "bb_upper": 422.0287,
        "bb_mid": 347.101,
        "bb_lower": 272.1733,
        "atr": 22.9447,
        "ma50": 306.5232,
        "ma200": NaN,
        "price": 372.56,
        "vol_ratio": 0.33,
        "above_ma50": true,
        "above_ma200": null
      },
      "patterns": {
        "candle": {
          "name": "bullish_engulfing",
          "direction": "bullish"
        },
        "bullish_divergence": false,
        "bearish_divergence": true,
        "bb_touch": "none",
        "volume_climax": false,
        "near_support": false,
        "near_resistance": false,
        "in_fib_zone": false
      },
      "trade_levels": {
        "entry": null,
        "stop_loss": null,
        "tp1": null,
        "tp2": null,
        "tp3": null,
        "risk": null,
        "rr_ratio": null,
        "trailing_stop": null,
        "trailing_k": 2.5
      },
      "support_levels": [
        152.61
      ],
      "resistance_levels": [
        188.94,
        338.37
      ],
      "fib_levels": {
        "0.0": 408.37,
        "23.6": 345.02,
        "38.2": 305.84,
        "50.0": 274.16,
        "61.8": 242.49,
        "78.6": 197.4,
        "100.0": 139.96
      }
    }
  },
  "yearly_trend": {
    "bias": "bullish",
    "ma200_position": "above",
    "structure": "uptrend (HH+HL)",
    "description": "Long-term trend bias \u2014 not a reversal call"
  }
}