{
  "ticker": "ICBP.JK",
  "market": "IHSG",
  "last_updated": "2026-07-17T05:35:19Z",
  "data_stale": false,
  "timeframes": {
    "daily": {
      "signal": "HOLD",
      "score": 47.8,
      "reason": "Neutral zone (47.8)",
      "components": {
        "rsi_stoch": 50.0,
        "divergence": 50.0,
        "candle_pattern": 50.0,
        "bb_touch": 50.0,
        "volume_climax": 50.0,
        "sr_fib": 35.0
      },
      "indicators": {
        "rsi": 58.2887,
        "stoch_k": 68.2194,
        "stoch_d": 65.2891,
        "macd": 70.0256,
        "macd_signal": 53.9232,
        "macd_hist": 16.1024,
        "bb_upper": 6848.5343,
        "bb_mid": 6551.1508,
        "bb_lower": 6253.7673,
        "atr": 167.3713,
        "ma50": 6495.7629,
        "ma200": 7502.1722,
        "price": 6725.0,
        "vol_ratio": 0.49,
        "above_ma50": true,
        "above_ma200": false
      },
      "patterns": {
        "candle": {
          "name": null,
          "direction": null
        },
        "bullish_divergence": false,
        "bearish_divergence": false,
        "bb_touch": "none",
        "volume_climax": false,
        "near_support": true,
        "near_resistance": true,
        "in_fib_zone": true
      },
      "trade_levels": {
        "entry": null,
        "stop_loss": null,
        "tp1": null,
        "tp2": null,
        "tp3": null,
        "risk": null,
        "rr_ratio": null,
        "trailing_stop": null,
        "trailing_k": 2.5
      },
      "support_levels": [
        6307.36,
        6575.0,
        6812.27
      ],
      "resistance_levels": [
        6881.81,
        7273.1
      ],
      "fib_levels": {
        "0.0": 7958.34,
        "23.6": 7424.96,
        "38.2": 7094.99,
        "50.0": 6828.3,
        "61.8": 6561.61,
        "78.6": 6181.92,
        "100.0": 5698.27
      }
    },
    "weekly": {
      "signal": "WATCH",
      "score": 66.0,
      "reason": "Elevated score (66.0) but not at confirmed range low | Bullish divergence detected | Candle: bullish_engulfing (bullish)",
      "components": {
        "rsi_stoch": 50.0,
        "divergence": 90.0,
        "candle_pattern": 90.0,
        "bb_touch": 50.0,
        "volume_climax": 50.0,
        "sr_fib": 50.0
      },
      "indicators": {
        "rsi": 44.6379,
        "stoch_k": 65.8674,
        "stoch_d": 57.2693,
        "macd": -343.3208,
        "macd_signal": -422.0637,
        "macd_hist": 78.743,
        "bb_upper": 7286.2388,
        "bb_mid": 6698.815,
        "bb_lower": 6111.3913,
        "atr": 403.009,
        "ma50": 7688.7116,
        "ma200": NaN,
        "price": 6725.0,
        "vol_ratio": 0.33,
        "above_ma50": false,
        "above_ma200": null
      },
      "patterns": {
        "candle": {
          "name": "bullish_engulfing",
          "direction": "bullish"
        },
        "bullish_divergence": true,
        "bearish_divergence": false,
        "bb_touch": "none",
        "volume_climax": false,
        "near_support": false,
        "near_resistance": false,
        "in_fib_zone": false
      },
      "trade_levels": {
        "entry": null,
        "stop_loss": null,
        "tp1": null,
        "tp2": null,
        "tp3": null,
        "risk": null,
        "rr_ratio": null,
        "trailing_stop": null,
        "trailing_k": 2.5
      },
      "support_levels": [
        9760.81,
        8210.79
      ],
      "resistance_levels": [
        11081.43,
        12079.22
      ],
      "fib_levels": {
        "0.0": 12090.96,
        "23.6": 10582.29,
        "38.2": 9648.95,
        "50.0": 8894.61,
        "61.8": 8140.28,
        "78.6": 7066.3,
        "100.0": 5698.27
      }
    }
  },
  "yearly_trend": {
    "bias": "volatile",
    "ma200_position": "below",
    "structure": "expanding (HH+LL)",
    "description": "Long-term trend bias \u2014 not a reversal call"
  }
}