{
  "ticker": "NFLX",
  "market": "US",
  "last_updated": "2026-07-21T05:44:13Z",
  "data_stale": false,
  "timeframes": {
    "daily": {
      "signal": "HOLD",
      "score": 55.5,
      "reason": "Neutral zone (55.5)",
      "components": {
        "rsi_stoch": 51.1,
        "divergence": 50.0,
        "candle_pattern": 50.0,
        "bb_touch": 85.0,
        "volume_climax": 50.0,
        "sr_fib": 50.0
      },
      "indicators": {
        "rsi": 28.6505,
        "stoch_k": 30.952,
        "stoch_d": 35.723,
        "macd": -2.5892,
        "macd_signal": -2.4118,
        "macd_hist": -0.1774,
        "bb_upper": 78.2171,
        "bb_mid": 73.392,
        "bb_lower": 68.5669,
        "atr": 2.7886,
        "ma50": 80.1484,
        "ma200": 93.4767,
        "price": 67.6,
        "vol_ratio": 1.13,
        "above_ma50": false,
        "above_ma200": false
      },
      "patterns": {
        "candle": {
          "name": null,
          "direction": null
        },
        "bullish_divergence": false,
        "bearish_divergence": false,
        "bb_touch": "lower",
        "volume_climax": false,
        "near_support": false,
        "near_resistance": false,
        "in_fib_zone": false
      },
      "trade_levels": {
        "entry": null,
        "stop_loss": null,
        "tp1": null,
        "tp2": null,
        "tp3": null,
        "risk": null,
        "rr_ratio": null,
        "trailing_stop": null,
        "trailing_k": 2.5
      },
      "support_levels": [
        90.35
      ],
      "resistance_levels": [
        95.52,
        101.44
      ],
      "fib_levels": {
        "0.0": 108.95,
        "23.6": 98.6,
        "38.2": 92.19,
        "50.0": 87.01,
        "61.8": 81.84,
        "78.6": 74.47,
        "100.0": 65.08
      }
    },
    "weekly": {
      "signal": "HOLD",
      "score": 53.1,
      "reason": "Neutral zone (53.1)",
      "components": {
        "rsi_stoch": 65.6,
        "divergence": 50.0,
        "candle_pattern": 50.0,
        "bb_touch": 50.0,
        "volume_climax": 50.0,
        "sr_fib": 50.0
      },
      "indicators": {
        "rsi": 29.7092,
        "stoch_k": 7.7201,
        "stoch_d": 9.8398,
        "macd": -6.9993,
        "macd_signal": -5.4302,
        "macd_hist": -1.5691,
        "bb_upper": 106.0772,
        "bb_mid": 85.7225,
        "bb_lower": 65.3678,
        "atr": 6.2142,
        "ma50": 96.6815,
        "ma200": NaN,
        "price": 67.6,
        "vol_ratio": 0.31,
        "above_ma50": false,
        "above_ma200": null
      },
      "patterns": {
        "candle": {
          "name": null,
          "direction": null
        },
        "bullish_divergence": false,
        "bearish_divergence": false,
        "bb_touch": "none",
        "volume_climax": false,
        "near_support": false,
        "near_resistance": false,
        "in_fib_zone": false
      },
      "trade_levels": {
        "entry": null,
        "stop_loss": null,
        "tp1": null,
        "tp2": null,
        "tp3": null,
        "risk": null,
        "rr_ratio": null,
        "trailing_stop": null,
        "trailing_k": 2.5
      },
      "support_levels": [
        82.23
      ],
      "resistance_levels": [
        98.08,
        107.7,
        125.78
      ],
      "fib_levels": {
        "0.0": 134.12,
        "23.6": 117.82,
        "38.2": 107.74,
        "50.0": 99.6,
        "61.8": 91.45,
        "78.6": 79.85,
        "100.0": 65.08
      }
    }
  },
  "yearly_trend": {
    "bias": "consolidating",
    "ma200_position": "below",
    "structure": "contracting (LH+HL)",
    "description": "Long-term trend bias \u2014 not a reversal call"
  }
}