{
  "ticker": "PYPL",
  "market": "US",
  "last_updated": "2026-07-15T05:25:33Z",
  "data_stale": false,
  "timeframes": {
    "daily": {
      "signal": "HOLD",
      "score": 46.7,
      "reason": "Neutral zone (46.7)",
      "components": {
        "rsi_stoch": 37.4,
        "divergence": 50.0,
        "candle_pattern": 50.0,
        "bb_touch": 50.0,
        "volume_climax": 50.0,
        "sr_fib": 45.0
      },
      "indicators": {
        "rsi": 63.9772,
        "stoch_k": 90.0617,
        "stoch_d": 87.2167,
        "macd": 0.852,
        "macd_signal": 0.3542,
        "macd_hist": 0.4978,
        "bb_upper": 47.6991,
        "bb_mid": 44.1475,
        "bb_lower": 40.5959,
        "atr": 1.4467,
        "ma50": 44.2142,
        "ma200": 52.7258,
        "price": 47.37,
        "vol_ratio": 0.58,
        "above_ma50": true,
        "above_ma200": false
      },
      "patterns": {
        "candle": {
          "name": null,
          "direction": null
        },
        "bullish_divergence": false,
        "bearish_divergence": false,
        "bb_touch": "none",
        "volume_climax": false,
        "near_support": false,
        "near_resistance": true,
        "in_fib_zone": true
      },
      "trade_levels": {
        "entry": null,
        "stop_loss": null,
        "tp1": null,
        "tp2": null,
        "tp3": null,
        "risk": null,
        "rr_ratio": null,
        "trailing_stop": null,
        "trailing_k": 2.5
      },
      "support_levels": [
        43.25,
        49.03
      ],
      "resistance_levels": [
        46.39,
        51.91
      ],
      "fib_levels": {
        "0.0": 52.13,
        "23.6": 49.31,
        "38.2": 47.57,
        "50.0": 46.16,
        "61.8": 44.76,
        "78.6": 42.75,
        "100.0": 40.2
      }
    },
    "weekly": {
      "signal": "HOLD",
      "score": 50.0,
      "reason": "Neutral zone (50.0)",
      "components": {
        "rsi_stoch": 50.0,
        "divergence": 50.0,
        "candle_pattern": 50.0,
        "bb_touch": 50.0,
        "volume_climax": 50.0,
        "sr_fib": 50.0
      },
      "indicators": {
        "rsi": 48.5268,
        "stoch_k": 51.866,
        "stoch_d": 42.579,
        "macd": -2.4162,
        "macd_signal": -3.3464,
        "macd_hist": 0.9302,
        "bb_upper": 50.6783,
        "bb_mid": 45.3673,
        "bb_lower": 40.0564,
        "atr": 3.3853,
        "ma50": 54.6637,
        "ma200": NaN,
        "price": 47.37,
        "vol_ratio": 0.41,
        "above_ma50": false,
        "above_ma200": null
      },
      "patterns": {
        "candle": {
          "name": null,
          "direction": null
        },
        "bullish_divergence": false,
        "bearish_divergence": false,
        "bb_touch": "none",
        "volume_climax": false,
        "near_support": false,
        "near_resistance": false,
        "in_fib_zone": false
      },
      "trade_levels": {
        "entry": null,
        "stop_loss": null,
        "tp1": null,
        "tp2": null,
        "tp3": null,
        "risk": null,
        "rr_ratio": null,
        "trailing_stop": null,
        "trailing_k": 2.5
      },
      "support_levels": [
        66.05,
        39.21,
        56.5
      ],
      "resistance_levels": [
        72.3,
        78.68,
        92.65
      ],
      "fib_levels": {
        "0.0": 92.86,
        "23.6": 79.96,
        "38.2": 71.98,
        "50.0": 65.54,
        "61.8": 59.09,
        "78.6": 49.91,
        "100.0": 38.22
      }
    }
  },
  "yearly_trend": {
    "bias": "bearish",
    "ma200_position": "below",
    "structure": "downtrend (LH+LL)",
    "description": "Long-term trend bias \u2014 not a reversal call"
  }
}