{
  "ticker": "SJM",
  "market": "US",
  "last_updated": "2026-07-22T05:43:51Z",
  "data_stale": false,
  "timeframes": {
    "daily": {
      "signal": "HOLD",
      "score": 53.0,
      "reason": "Neutral zone (53.0) | Candle: morning_star (bullish)",
      "components": {
        "rsi_stoch": 50.0,
        "divergence": 50.0,
        "candle_pattern": 90.0,
        "bb_touch": 50.0,
        "volume_climax": 50.0,
        "sr_fib": 30.0
      },
      "indicators": {
        "rsi": 59.0694,
        "stoch_k": 59.1089,
        "stoch_d": 51.8224,
        "macd": 1.1228,
        "macd_signal": 1.2862,
        "macd_hist": -0.1634,
        "bb_upper": 117.0321,
        "bb_mid": 112.6025,
        "bb_lower": 108.1729,
        "atr": 3.2686,
        "ma50": 108.1332,
        "ma200": 102.4212,
        "price": 115.75,
        "vol_ratio": 1.25,
        "above_ma50": true,
        "above_ma200": true
      },
      "patterns": {
        "candle": {
          "name": "morning_star",
          "direction": "bullish"
        },
        "bullish_divergence": false,
        "bearish_divergence": false,
        "bb_touch": "none",
        "volume_climax": false,
        "near_support": false,
        "near_resistance": true,
        "in_fib_zone": false
      },
      "trade_levels": {
        "entry": null,
        "stop_loss": null,
        "tp1": null,
        "tp2": null,
        "tp3": null,
        "risk": null,
        "rr_ratio": null,
        "trailing_stop": null,
        "trailing_k": 2.5
      },
      "support_levels": [
        99.03,
        107.27
      ],
      "resistance_levels": [
        104.78,
        117.5
      ],
      "fib_levels": {
        "0.0": 118.08,
        "23.6": 110.81,
        "38.2": 106.31,
        "50.0": 102.68,
        "61.8": 99.05,
        "78.6": 93.87,
        "100.0": 87.28
      }
    },
    "weekly": {
      "signal": "HOLD",
      "score": 51.9,
      "reason": "Neutral zone (51.9) | Candle: bullish_engulfing (bullish)",
      "components": {
        "rsi_stoch": 44.6,
        "divergence": 50.0,
        "candle_pattern": 90.0,
        "bb_touch": 50.0,
        "volume_climax": 50.0,
        "sr_fib": 30.0
      },
      "indicators": {
        "rsi": 61.5599,
        "stoch_k": 84.3028,
        "stoch_d": 86.3665,
        "macd": 3.4852,
        "macd_signal": 2.0166,
        "macd_hist": 1.4686,
        "bb_upper": 121.2132,
        "bb_mid": 103.7263,
        "bb_lower": 86.2394,
        "atr": 6.4539,
        "ma50": 103.7197,
        "ma200": NaN,
        "price": 115.75,
        "vol_ratio": 0.36,
        "above_ma50": true,
        "above_ma200": null
      },
      "patterns": {
        "candle": {
          "name": "bullish_engulfing",
          "direction": "bullish"
        },
        "bullish_divergence": false,
        "bearish_divergence": false,
        "bb_touch": "none",
        "volume_climax": false,
        "near_support": false,
        "near_resistance": true,
        "in_fib_zone": false
      },
      "trade_levels": {
        "entry": null,
        "stop_loss": null,
        "tp1": null,
        "tp2": null,
        "tp3": null,
        "risk": null,
        "rr_ratio": null,
        "trailing_stop": null,
        "trailing_k": 2.5
      },
      "support_levels": [
        95.83
      ],
      "resistance_levels": [
        114.84
      ],
      "fib_levels": {
        "0.0": 118.08,
        "23.6": 110.81,
        "38.2": 106.31,
        "50.0": 102.68,
        "61.8": 99.05,
        "78.6": 93.87,
        "100.0": 87.28
      }
    }
  },
  "yearly_trend": {
    "bias": "consolidating",
    "ma200_position": "above",
    "structure": "contracting (LH+HL)",
    "description": "Long-term trend bias \u2014 not a reversal call"
  }
}