{
  "ticker": "WMT",
  "market": "US",
  "last_updated": "2026-07-21T05:44:17Z",
  "data_stale": false,
  "timeframes": {
    "daily": {
      "signal": "HOLD",
      "score": 60.0,
      "reason": "Neutral zone (60.0) | Bullish divergence detected",
      "components": {
        "rsi_stoch": 50.0,
        "divergence": 90.0,
        "candle_pattern": 50.0,
        "bb_touch": 50.0,
        "volume_climax": 50.0,
        "sr_fib": 50.0
      },
      "indicators": {
        "rsi": 41.8973,
        "stoch_k": 60.8614,
        "stoch_d": 59.3549,
        "macd": -1.5884,
        "macd_signal": -1.966,
        "macd_hist": 0.3776,
        "bb_upper": 119.2262,
        "bb_mid": 113.9695,
        "bb_lower": 108.7128,
        "atr": 2.8239,
        "ma50": 119.2804,
        "ma200": 117.2515,
        "price": 112.2,
        "vol_ratio": 0.79,
        "above_ma50": false,
        "above_ma200": false
      },
      "patterns": {
        "candle": {
          "name": null,
          "direction": null
        },
        "bullish_divergence": true,
        "bearish_divergence": false,
        "bb_touch": "none",
        "volume_climax": false,
        "near_support": false,
        "near_resistance": false,
        "in_fib_zone": false
      },
      "trade_levels": {
        "entry": null,
        "stop_loss": null,
        "tp1": null,
        "tp2": null,
        "tp3": null,
        "risk": null,
        "rr_ratio": null,
        "trailing_stop": null,
        "trailing_k": 2.5
      },
      "support_levels": [
        121.59,
        117.66,
        126.03
      ],
      "resistance_levels": [
        130.81,
        121.41
      ],
      "fib_levels": {
        "0.0": 135.16,
        "23.6": 128.57,
        "38.2": 124.5,
        "50.0": 121.21,
        "61.8": 117.91,
        "78.6": 113.22,
        "100.0": 107.25
      }
    },
    "weekly": {
      "signal": "HOLD",
      "score": 47.0,
      "reason": "Neutral zone (47.0) | Candle: evening_star (bearish)",
      "components": {
        "rsi_stoch": 50.0,
        "divergence": 50.0,
        "candle_pattern": 10.0,
        "bb_touch": 50.0,
        "volume_climax": 50.0,
        "sr_fib": 70.0
      },
      "indicators": {
        "rsi": 42.3684,
        "stoch_k": 22.2023,
        "stoch_d": 20.5992,
        "macd": -1.0113,
        "macd_signal": 1.009,
        "macd_hist": -2.0203,
        "bb_upper": 134.76,
        "bb_mid": 121.5349,
        "bb_lower": 108.3097,
        "atr": 6.2083,
        "ma50": 114.7755,
        "ma200": NaN,
        "price": 112.2,
        "vol_ratio": 0.18,
        "above_ma50": false,
        "above_ma200": null
      },
      "patterns": {
        "candle": {
          "name": "evening_star",
          "direction": "bearish"
        },
        "bullish_divergence": false,
        "bearish_divergence": false,
        "bb_touch": "none",
        "volume_climax": false,
        "near_support": true,
        "near_resistance": false,
        "in_fib_zone": false
      },
      "trade_levels": {
        "entry": null,
        "stop_loss": null,
        "tp1": null,
        "tp2": null,
        "tp3": null,
        "risk": null,
        "rr_ratio": null,
        "trailing_stop": null,
        "trailing_k": 2.5
      },
      "support_levels": [
        94.56,
        111.79
      ],
      "resistance_levels": [
        101.76,
        119.96,
        134.66
      ],
      "fib_levels": {
        "0.0": 135.16,
        "23.6": 120.82,
        "38.2": 111.95,
        "50.0": 104.78,
        "61.8": 97.61,
        "78.6": 87.4,
        "100.0": 74.39
      }
    }
  },
  "yearly_trend": {
    "bias": "bearish",
    "ma200_position": "above",
    "structure": "downtrend (LH+LL)",
    "description": "Long-term trend bias \u2014 not a reversal call"
  }
}