{
  "ticker": "XEL",
  "market": "US",
  "last_updated": "2026-07-14T12:00:31Z",
  "data_stale": false,
  "timeframes": {
    "daily": {
      "signal": "HOLD",
      "score": 47.0,
      "reason": "Neutral zone (47.0)",
      "components": {
        "rsi_stoch": 50.0,
        "divergence": 50.0,
        "candle_pattern": 50.0,
        "bb_touch": 50.0,
        "volume_climax": 50.0,
        "sr_fib": 30.0
      },
      "indicators": {
        "rsi": 53.018,
        "stoch_k": 42.9643,
        "stoch_d": 44.9869,
        "macd": 0.3518,
        "macd_signal": 0.4375,
        "macd_hist": -0.0857,
        "bb_upper": 82.8602,
        "bb_mid": 80.0289,
        "bb_lower": 77.1975,
        "atr": 1.6046,
        "ma50": 79.3888,
        "ma200": 78.0236,
        "price": 80.48,
        "vol_ratio": 0.77,
        "above_ma50": true,
        "above_ma200": true
      },
      "patterns": {
        "candle": {
          "name": null,
          "direction": null
        },
        "bullish_divergence": false,
        "bearish_divergence": false,
        "bb_touch": "none",
        "volume_climax": false,
        "near_support": false,
        "near_resistance": true,
        "in_fib_zone": false
      },
      "trade_levels": {
        "entry": null,
        "stop_loss": null,
        "tp1": null,
        "tp2": null,
        "tp3": null,
        "risk": null,
        "rr_ratio": null,
        "trailing_stop": null,
        "trailing_k": 2.5
      },
      "support_levels": [
        77.54
      ],
      "resistance_levels": [
        81.8
      ],
      "fib_levels": {
        "0.0": 83.22,
        "23.6": 81.42,
        "38.2": 80.31,
        "50.0": 79.41,
        "61.8": 78.51,
        "78.6": 77.22,
        "100.0": 75.59
      }
    },
    "weekly": {
      "signal": "HOLD",
      "score": 47.0,
      "reason": "Neutral zone (47.0)",
      "components": {
        "rsi_stoch": 50.0,
        "divergence": 50.0,
        "candle_pattern": 50.0,
        "bb_touch": 50.0,
        "volume_climax": 50.0,
        "sr_fib": 30.0
      },
      "indicators": {
        "rsi": 53.9234,
        "stoch_k": 68.6993,
        "stoch_d": 69.9367,
        "macd": 1.022,
        "macd_signal": 1.093,
        "macd_hist": -0.071,
        "bb_upper": 83.2946,
        "bb_mid": 79.6958,
        "bb_lower": 76.097,
        "atr": 3.3873,
        "ma50": 77.1635,
        "ma200": NaN,
        "price": 80.48,
        "vol_ratio": 0.19,
        "above_ma50": true,
        "above_ma200": null
      },
      "patterns": {
        "candle": {
          "name": null,
          "direction": null
        },
        "bullish_divergence": false,
        "bearish_divergence": false,
        "bb_touch": "none",
        "volume_climax": false,
        "near_support": false,
        "near_resistance": true,
        "in_fib_zone": false
      },
      "trade_levels": {
        "entry": null,
        "stop_loss": null,
        "tp1": null,
        "tp2": null,
        "tp3": null,
        "risk": null,
        "rr_ratio": null,
        "trailing_stop": null,
        "trailing_k": 2.5
      },
      "support_levels": [
        64.5,
        76.16
      ],
      "resistance_levels": [
        70.28,
        82.56
      ],
      "fib_levels": {
        "0.0": 83.22,
        "23.6": 76.78,
        "38.2": 72.79,
        "50.0": 69.57,
        "61.8": 66.35,
        "78.6": 61.76,
        "100.0": 55.92
      }
    }
  },
  "yearly_trend": {
    "bias": "bullish",
    "ma200_position": "above",
    "structure": "uptrend (HH+HL)",
    "description": "Long-term trend bias \u2014 not a reversal call"
  }
}